colorfullog/__init__.py
colorfullog/colorfullog.py
colorfullog-0.0.5.dist-info/METADATA
colorfullog-0.0.5.dist-info/WHEEL
colorfullog-0.0.5.dist-info/top_level.txt
colorfullog-0.0.5.dist-info/RECORD
